cfmetrics
tests
