Metadata-Version: 2.2
Name: cfmetrics
Version: 0.2.1
Summary: Python Library for cloudflare analytics web
Home-page: https://github.com/k1m0ch1/cloudflare-analytics
Author: k1m0ch1
Author-email: yahya.kimochi@gmail.com
Requires-Python: >=3.7
License-File: LICENSE
Requires-Dist: requests
Dynamic: author
Dynamic: author-email
Dynamic: description
Dynamic: description-content-type
Dynamic: home-page
Dynamic: requires-dist
Dynamic: requires-python
Dynamic: summary
